Metadata-Version: 2.1
Name: seqcluster
Version: 1.2.5
Summary: Small RNA-seq pipeline
Home-page: http://github.com/lpantano/seqcluster
Author: Lorena Pantano
Author-email: lorena.pantano@gmail.com
License: MIT
Keywords: RNA-seq miRNA snoRNA NGS
Platform: UNKNOWN
Classifier: License :: OSI Approved :: MIT License
Classifier: Programming Language :: Python :: 2.7
Classifier: Topic :: Scientific/Engineering :: Bio-Informatics
